intake_civis/__init__.py
intake_civis/_version.py
intake_civis/alchemy.py
intake_civis/driver.py
intake_civis/ibis.py
intake_civis-0.2.0.dist-info/LICENSE
intake_civis-0.2.0.dist-info/METADATA
intake_civis-0.2.0.dist-info/WHEEL
intake_civis-0.2.0.dist-info/entry_points.txt
intake_civis-0.2.0.dist-info/top_level.txt
intake_civis-0.2.0.dist-info/RECORD
