Metadata-Version: 2.1
Name: intake-civis
Version: 0.2.0
Summary: Intake driver for Civis platform
Home-page: https://github.com/CityOfLosAngeles/intake-civis
Maintainer: Ian Rose
Maintainer-email: ian.rose@lacity.org
License: Apache-2.0 license
Keywords: intake civis
Platform: UNKNOWN
Requires-Dist: civis
Requires-Dist: intake
Provides-Extra: geospatial
Requires-Dist: geopandas ; extra == 'geospatial'
Requires-Dist: shapely ; extra == 'geospatial'
Provides-Extra: ibis
Requires-Dist: ibis-framework ; extra == 'ibis'
Requires-Dist: sqlalchemy ; extra == 'ibis'
Requires-Dist: sqlalchemy-redshift ; extra == 'ibis'
